{
    "title_id": "OOPP54321",
    "name": "Home",
    "updated_at": "2020-05-01",
    "authors": [
        {
            "name": "Paulo",
            "type": "author"
        }
    ],
    "icons": [
        "https:\/\/gitlab.com\/SilicaAndPina\/cbpsdb\/-\/raw\/master\/icon0\/OOPP54321_icon0.png"
    ],
    "downloads": [
        "https:\/\/gitlab.com\/SilicaAndPina\/cbpsdb\/-\/raw\/master\/vpk\/OOPP54321.vpk"
    ],
    "type": "game",
    "description": "A port of Get the F off my lawn for PSVITA\/PSTV.\nDefend your home from Big Bad Wolves.",
    "version": "v.1.0",
    "license": "Unknown"
}