{
    "title_id": "DUNGEON00",
    "name": "DungeonRush",
    "updated_at": "2020-09-12",
    "authors": [
        {
            "name": "xfangfang",
            "type": "author"
        }
    ],
    "icons": [
        "https:\/\/github.com\/xfangfang\/DungeonRush-PSV\/raw\/master\/psv\/icon0_dark_128.png"
    ],
    "downloads": [
        "https:\/\/github.com\/xfangfang\/DungeonRush-PSV\/releases\/download\/01.00\/dungeonrush_01.00.vpk"
    ],
    "repos": [
        "https:\/\/github.com\/xfangfang\/DungeonRush-PSV\/"
    ],
    "type": "game",
    "description": "Port of Dungeon Rush for PSVita.\nDungeon Rush is a game inspired by Snake.",
    "version": "01.00",
    "license": "GPL3"
}